{"name":"Frame","tagline":"Micro less framework","body":"# Frame\r\nMicro less framework\r\n\r\n## Внешние библиотеки\r\n\r\n+ Eric Meyer's Reset CSS v2.0\r\n+ LESS Hat 1.1.1\r\n\r\n## Особенности\r\n\r\n+ Ничего лишнего, а что есть можно отключить.\r\n+ Подавляющее количества насторек вынесены в отдельный файл настроек (variables.less).\r\n+ Все исходники на .less, используя его преимущества раскрываются основные возможности фреймворка.\r\n+ В сетке используется правило border-box\r\n+ Любое количество колонок в сетке (в примере 12) - задается через параметр в файле настроек как и ширина отступов между колонками.\r\n+ Сетка процентная (можно поменять как формулу так и единицы измерения в соответствующем файле (grid))\r\n+ В примере подключено 5 @media режимов для которых можно через файл настроек изменить лимиты.\r\n+ Именование колонок col-1, col-2 и т.д.\r\n+ Для ссылок, шрифтов, сетки, а так же заголовков (на данный момент) less-классы и less-переменные облегчающие настройку и модификацию под свои нужды.\r\n\r\n## Автор\r\n**Eugene 'kaaboeld' Popov**\r\n\r\n+ https://github.com/kaaboeld/frame\r\n+ http://scrw.co\r\n\r\n## Лицензия\r\n\r\n+ http://www.apache.org/licenses/LICENSE-2.0\r\n","google":"UA-41574974-1","note":"Don't delete this file! It's used internally to help with page regeneration."}